macpm/__init__.py
macpm/macpm.py
macpm-0.24.dist-info/LICENSE
macpm-0.24.dist-info/METADATA
macpm-0.24.dist-info/WHEEL
macpm-0.24.dist-info/entry_points.txt
macpm-0.24.dist-info/top_level.txt
macpm-0.24.dist-info/RECORD
