Metadata-Version: 2.1
Name: macpm
Version: 0.24
Summary: Performance monitoring CLI tool for Apple Silicon
Home-page: https://github.com/visualcjy/macpm
Author: Jinyu Chen
Author-email: visualcjy@mail.com
License: MIT
Keywords: macpm
Classifier: Programming Language :: Python :: 3
Classifier: License :: OSI Approved :: MIT License
Classifier: Operating System :: MacOS
License-File: LICENSE
Requires-Dist: dashing
Requires-Dist: psutil
Requires-Dist: humanize
